scvalue/__init__.py
scvalue/scvalue.py
scvalue-0.1.0.dist-info/licenses/LICENSE
scvalue-0.1.0.dist-info/METADATA
scvalue-0.1.0.dist-info/WHEEL
scvalue-0.1.0.dist-info/top_level.txt
scvalue-0.1.0.dist-info/RECORD
