Metadata-Version: 2.4
Name: scvalue
Version: 0.1.0
Summary: scValue: value-based subsampling of large-scale single-cell transcriptomic data for machine and deep learning tasks
Home-page: https://github.com/lhbcb/scvalue
Author: Li Huang
Author-email: hl@ism.cams.cn
License: BSD-3-Clause
Classifier: Programming Language :: Python :: 3
Classifier: License :: OSI Approved :: BSD License
Classifier: Operating System :: OS Independent
Requires-Python: >=3.10
License-File: LICENSE
Requires-Dist: scikit-learn<2.0,>=1.5.2
Requires-Dist: scipy<2.0,>=1.14.0
Requires-Dist: numpy<3.0,>=1.26.4
Requires-Dist: pandas<3.0,>=1.5.3
Requires-Dist: joblib<2.0,>=1.4.2
Requires-Dist: scanpy<2.0,>=1.10.2
Requires-Dist: anndata<0.13,>=0.10.8
Dynamic: author
Dynamic: author-email
Dynamic: classifier
Dynamic: description
Dynamic: description-content-type
Dynamic: home-page
Dynamic: license
Dynamic: license-file
Dynamic: requires-dist
Dynamic: requires-python
Dynamic: summary
